split_markdown4gpt/__init__.py
split_markdown4gpt/__main__.py
split_markdown4gpt/splitter.py
split_markdown4gpt-1.0.9.dist-info/LICENSE.txt
split_markdown4gpt-1.0.9.dist-info/METADATA
split_markdown4gpt-1.0.9.dist-info/WHEEL
split_markdown4gpt-1.0.9.dist-info/entry_points.txt
split_markdown4gpt-1.0.9.dist-info/top_level.txt
split_markdown4gpt-1.0.9.dist-info/RECORD
