Metadata-Version: 2.1
Name: split-markdown4gpt
Version: 1.0.9
Summary: A Python tool for splitting large Markdown files into smaller sections based on a specified token limit. This is particularly useful for processing large Markdown files with GPT models, as it allows the models to handle the data in manageable chunks.
Home-page: https://github.com/twardoch/split-markdown4gpt
Author: Adam Twardoch
Author-email: adam+github@twardoch.com
License: Apache-2.0
Project-URL: Documentation, https://twardoch.github.io/split-markdown4gpt/
Project-URL: Source, https://github.com/twardoch/split-markdown4gpt
Keywords: python,nlp,markdown,natural-language-processing,text-analysis,openai,text-summarization,summarization,text-processing,gpt,data-preprocessing,mistletoe,split-text,text-tokenization,openai-gpt,gpt-3,gpt-4,gpt-35-turbo,gpt-35-turbo-16k,markdown-processing
Platform: any
Classifier: Development Status :: 4 - Beta
Classifier: Programming Language :: Python
Classifier: Programming Language :: Python :: 3
Classifier: Programming Language :: Python :: 3.10
Classifier: Intended Audience :: Developers
Classifier: Intended Audience :: Science/Research
Classifier: Topic :: Text Processing
Classifier: Topic :: Text Processing :: Markup :: Markdown
Classifier: License :: OSI Approved :: Apache Software License
Classifier: Operating System :: OS Independent
Requires-Python: >=3.10
License-File: LICENSE.txt
Requires-Dist: fire (>=0.5.0)
Requires-Dist: mistletoe (>=1.1.0)
Requires-Dist: python-frontmatter (>=1.0.0)
Requires-Dist: PyYAML (>=5.1)
Requires-Dist: regex (>=2023.6.3)
Requires-Dist: syntok (>=1.4.4)
Requires-Dist: tiktoken (>=0.4.0)
Requires-Dist: importlib-metadata ; python_version < "3.8"
Provides-Extra: testing
Requires-Dist: setuptools ; extra == 'testing'
Requires-Dist: pytest ; extra == 'testing'
Requires-Dist: pytest-cov ; extra == 'testing'
